{
    "metric": {
        "exception": {
            "n": 6,
            "skipped": 0,
            "top-1": 0.5,
            "top-2": 0.5,
            "top-3": 0.5,
            "top-4": 0.5,
            "top-5": 0.5,
            "avg@5": 0.5,
            "avg_rank": 4.5
        },
        "code_delay": {
            "n": 10,
            "skipped": 0,
            "top-1": 0.6,
            "top-2": 0.6,
            "top-3": 0.7,
            "top-4": 0.7,
            "top-5": 0.7,
            "avg@5": 0.6599999999999999,
            "avg_rank": 3.5
        },
        "all": {
            "n": 16,
            "skipped": 0,
            "top-1": 0.5625,
            "top-2": 0.5625,
            "top-3": 0.625,
            "top-4": 0.625,
            "top-5": 0.625,
            "avg@5": 0.6,
            "avg_rank": 3.875
        }
    },
    "detail": [
        {
            "timestamp": 1714027200,
            "level": "pod",
            "cmdb_id": "ts-contacts-service-866bd68c97-b6rfg",
            "failure_type": "code_delay",
            "cand": [
                {
                    "ntype": "api",
                    "id": 43,
                    "score": 16.28066821549263,
                    "path": "api: ts-contacts-service-ContactsController.getContactsByContactsId --8.24--> api: ts-contacts-service-HTTP GET /api/v1/contactservice/contacts/{id} --12.89--> api: ts-preserve-other-service-HTTP GET /api/v1/contactservice/contacts/{id}",
                    "name": "ts-contacts-service-ContactsController.getContactsByContactsId"
                },
                {
                    "ntype": "api",
                    "id": 45,
                    "score": 7.870587215924744,
                    "path": "api: ts-contacts-service-HTTP GET /api/v1/contactservice/contacts/{id} --12.89--> api: ts-preserve-other-service-HTTP GET /api/v1/contactservice/contacts/{id}",
                    "name": "ts-contacts-service-HTTP GET /api/v1/contactservice/contacts/{id}"
                },
                {
                    "ntype": "api",
                    "id": 2,
                    "score": 6.8012085038466,
                    "name": "ts-assurance-service-AssuranceRepository.save"
                },
                {
                    "ntype": "api",
                    "id": 58,
                    "score": 6.2507195857226865,
                    "name": "ts-execute-service-HTTP GET /api/v1/executeservice/execute/collected/{orderId}"
                },
                {
                    "ntype": "api",
                    "id": 112,
                    "score": 6.083493483505687,
                    "name": "ts-inside-payment-service-Session.persist inside_payment.entity.Money"
                },
                {
                    "ntype": "api",
                    "id": 75,
                    "score": 4.602296668423258,
                    "path": "api: ts-food-service-INSERT ts.food_order --2.85--> api: ts-food-service-Transaction.commit",
                    "name": "ts-food-service-INSERT ts.food_order"
                },
                {
                    "ntype": "api",
                    "id": 181,
                    "score": 3.114214769104353,
                    "path": "api: ts-preserve-other-service-PreserveOtherController.preserve --3.96--> api: ts-preserve-other-service-HTTP POST /api/v1/preserveotherservice/preserveOther --2.77--> api: ts-gateway-service-HTTP POST /api/v1/preserveotherservice/preserveOther",
                    "name": "ts-preserve-other-service-PreserveOtherController.preserve"
                },
                {
                    "ntype": "pod",
                    "id": 3,
                    "score": 3.0605444153194696,
                    "name": "ts-cancel-service-756f6c4675-n8l65"
                },
                {
                    "ntype": "pod",
                    "id": 24,
                    "score": 3.040875108825308,
                    "name": "ts-travel-service-64469b5b48-zbwtm"
                },
                {
                    "ntype": "api",
                    "id": 124,
                    "score": 2.791911786132244,
                    "name": "ts-order-other-service-OrderOtherController.getTicketListByDateAndTripId"
                }
            ]
        },
        {
            "timestamp": 1714030860,
            "level": "pod",
            "cmdb_id": "ts-travel-service-64469b5b48-zbwtm",
            "failure_type": "code_delay",
            "cand": [
                {
                    "ntype": "pod",
                    "id": 24,
                    "score": 80.65356680889272,
                    "path": "pod: ts-travel-service-64469b5b48-zbwtm --41.73--> api: ts-travel-service-Transaction.commit",
                    "name": "ts-travel-service-64469b5b48-zbwtm"
                },
                {
                    "ntype": "api",
                    "id": 268,
                    "score": 10.693486344904647,
                    "path": "api: ts-travel-service-Transaction.commit",
                    "name": "ts-travel-service-Transaction.commit"
                },
                {
                    "ntype": "api",
                    "id": 181,
                    "score": 10.528799508895897,
                    "name": "ts-preserve-other-service-PreserveOtherController.preserve"
                },
                {
                    "ntype": "api",
                    "id": 258,
                    "score": 7.610111600603908,
                    "path": "api: ts-travel-service-BasicErrorController.error",
                    "name": "ts-travel-service-BasicErrorController.error"
                },
                {
                    "ntype": "api",
                    "id": 112,
                    "score": 7.048053277960654,
                    "name": "ts-inside-payment-service-Session.persist inside_payment.entity.Money"
                },
                {
                    "ntype": "api",
                    "id": 58,
                    "score": 6.187718158621758,
                    "name": "ts-execute-service-HTTP GET /api/v1/executeservice/execute/collected/{orderId}"
                },
                {
                    "ntype": "api",
                    "id": 271,
                    "score": 5.08053886358618,
                    "path": "api: ts-travel-service-TravelController.queryInfo --4.11--> api: ts-travel-service-HTTP POST /api/v1/travelservice/trips/left --3.20--> api: ts-gateway-service-HTTP POST /api/v1/travelservice/trips/left",
                    "name": "ts-travel-service-TravelController.queryInfo"
                },
                {
                    "ntype": "pod",
                    "id": 6,
                    "score": 4.914971439916435,
                    "name": "ts-delivery-service-7d97b69596-jngz4"
                },
                {
                    "ntype": "pod",
                    "id": 3,
                    "score": 4.547358086277683,
                    "name": "ts-cancel-service-756f6c4675-n8l65"
                },
                {
                    "ntype": "api",
                    "id": 265,
                    "score": 4.366769985139682,
                    "path": "api: ts-travel-service-HTTP POST /api/v1/travelservice/trips/left --3.20--> api: ts-gateway-service-HTTP POST /api/v1/travelservice/trips/left",
                    "name": "ts-travel-service-HTTP POST /api/v1/travelservice/trips/left"
                }
            ]
        },
        {
            "timestamp": 1714033200,
            "level": "pod",
            "cmdb_id": "ts-order-service-5b67c48447-4d4rx",
            "failure_type": "code_delay",
            "cand": [
                {
                    "ntype": "api",
                    "id": 146,
                    "score": 36.625183842407715,
                    "path": "api: ts-order-service-OrderController.getOrderById --11.08--> api: ts-order-service-HTTP GET /api/v1/orderservice/order/{orderId} --30.94--> api: ts-cancel-service-HTTP GET /api/v1/orderservice/order/{orderId} --3.96--> api: ts-cancel-service-CancelController.cancelTicket",
                    "name": "ts-order-service-OrderController.getOrderById"
                },
                {
                    "ntype": "api",
                    "id": 140,
                    "score": 18.381563487667755,
                    "path": "api: ts-order-service-HTTP GET /api/v1/orderservice/order/{orderId} --30.94--> api: ts-cancel-service-HTTP GET /api/v1/orderservice/order/{orderId} --3.96--> api: ts-cancel-service-CancelController.cancelTicket",
                    "name": "ts-order-service-HTTP GET /api/v1/orderservice/order/{orderId}"
                },
                {
                    "ntype": "api",
                    "id": 58,
                    "score": 10.24420003602045,
                    "path": "api: ts-execute-service-HTTP GET /api/v1/executeservice/execute/collected/{orderId} --5.19--> api: ts-gateway-service-HTTP GET /api/v1/executeservice/execute/collected/{orderId} --1.71--> api: ts-gateway-service-/*",
                    "name": "ts-execute-service-HTTP GET /api/v1/executeservice/execute/collected/{orderId}"
                },
                {
                    "ntype": "api",
                    "id": 233,
                    "score": 8.259609466721734,
                    "path": "api: ts-station-food-service-StationFoodController.getFoodStoresByStationNames --4.69--> api: ts-station-food-service-HTTP POST /api/v1/stationfoodservice/stationfoodstores --4.27--> api: ts-food-service-HTTP POST /api/v1/stationfoodservice/stationfoodstores",
                    "name": "ts-station-food-service-StationFoodController.getFoodStoresByStationNames"
                },
                {
                    "ntype": "api",
                    "id": 1,
                    "score": 7.680021643558657,
                    "path": "api: ts-assurance-service-AssuranceRepository.findByOrderId",
                    "name": "ts-assurance-service-AssuranceRepository.findByOrderId"
                },
                {
                    "ntype": "api",
                    "id": 57,
                    "score": 6.298642056633081,
                    "path": "api: ts-execute-service-ExecuteControlller.executeTicket --5.71--> api: ts-execute-service-HTTP GET /api/v1/executeservice/execute/execute/{orderId} --5.72--> api: ts-gateway-service-HTTP GET /api/v1/executeservice/execute/execute/{orderId}",
                    "name": "ts-execute-service-ExecuteControlller.executeTicket"
                },
                {
                    "ntype": "api",
                    "id": 143,
                    "score": 5.699915189373621,
                    "name": "ts-order-service-HTTP PUT /api/v1/orderservice/order"
                },
                {
                    "ntype": "api",
                    "id": 5,
                    "score": 4.740371501078459,
                    "path": "api: ts-assurance-service-SELECT Assurance --3.59--> api: ts-assurance-service-AssuranceRepository.findByOrderId",
                    "name": "ts-assurance-service-SELECT Assurance"
                },
                {
                    "ntype": "api",
                    "id": 230,
                    "score": 4.194838298808843,
                    "path": "api: ts-station-food-service-HTTP POST /api/v1/stationfoodservice/stationfoodstores --4.27--> api: ts-food-service-HTTP POST /api/v1/stationfoodservice/stationfoodstores",
                    "name": "ts-station-food-service-HTTP POST /api/v1/stationfoodservice/stationfoodstores"
                },
                {
                    "ntype": "api",
                    "id": 264,
                    "score": 4.073969278109669,
                    "name": "ts-travel-service-HTTP POST /api/v1/travelservice/trip_detail"
                }
            ]
        },
        {
            "timestamp": 1714038960,
            "level": "pod",
            "cmdb_id": "ts-travel2-service-5c66d57d58-klvkm",
            "failure_type": "code_delay",
            "cand": [
                {
                    "ntype": "api",
                    "id": 284,
                    "score": 10.87085345060239,
                    "path": "api: ts-travel2-service-Travel2Controller.queryInfo --5.85--> api: ts-travel2-service-HTTP POST /api/v1/travel2service/trips/left --6.07--> api: ts-gateway-service-HTTP POST /api/v1/travel2service/trips/left --5.78--> api: ts-gateway-service-/*",
                    "name": "ts-travel2-service-Travel2Controller.queryInfo"
                },
                {
                    "ntype": "api",
                    "id": 57,
                    "score": 5.773393468868647,
                    "path": "api: ts-execute-service-ExecuteControlller.executeTicket --4.44--> api: ts-execute-service-HTTP GET /api/v1/executeservice/execute/execute/{orderId} --4.44--> api: ts-gateway-service-HTTP GET /api/v1/executeservice/execute/execute/{orderId}",
                    "name": "ts-execute-service-ExecuteControlller.executeTicket"
                },
                {
                    "ntype": "api",
                    "id": 56,
                    "score": 5.1034052090727675,
                    "name": "ts-execute-service-ExecuteControlller.collectTicket"
                },
                {
                    "ntype": "api",
                    "id": 279,
                    "score": 4.959807195111448,
                    "path": "api: ts-travel2-service-HTTP POST /api/v1/travel2service/trips/left --6.07--> api: ts-gateway-service-HTTP POST /api/v1/travel2service/trips/left --5.78--> api: ts-gateway-service-/*",
                    "name": "ts-travel2-service-HTTP POST /api/v1/travel2service/trips/left"
                },
                {
                    "ntype": "api",
                    "id": 63,
                    "score": 4.733972354291841,
                    "name": "ts-execute-service-HTTP GET /api/v1/orderservice/order/{orderId}"
                },
                {
                    "ntype": "api",
                    "id": 112,
                    "score": 4.543842118483452,
                    "name": "ts-inside-payment-service-Session.persist inside_payment.entity.Money"
                },
                {
                    "ntype": "api",
                    "id": 58,
                    "score": 4.437503612244698,
                    "name": "ts-execute-service-HTTP GET /api/v1/executeservice/execute/collected/{orderId}"
                },
                {
                    "ntype": "api",
                    "id": 135,
                    "score": 3.9382256411067793,
                    "name": "ts-order-other-service-Session.merge other.entity.Order"
                },
                {
                    "ntype": "api",
                    "id": 89,
                    "score": 3.8247361518620493,
                    "path": "api: ts-gateway-service-HTTP POST /api/v1/travel2service/trips/left --5.78--> api: ts-gateway-service-/*",
                    "name": "ts-gateway-service-HTTP POST /api/v1/travel2service/trips/left"
                },
                {
                    "ntype": "api",
                    "id": 80,
                    "score": 3.2292718112282284,
                    "path": "api: ts-gateway-service-/*",
                    "name": "ts-gateway-service-/*"
                }
            ]
        },
        {
            "timestamp": 1714044600,
            "level": "pod",
            "cmdb_id": "ts-travel2-service-5c66d57d58-klvkm",
            "failure_type": "code_delay",
            "cand": [
                {
                    "ntype": "api",
                    "id": 284,
                    "score": 12.699348403457765,
                    "path": "api: ts-travel2-service-Travel2Controller.queryInfo --5.97--> api: ts-travel2-service-HTTP POST /api/v1/travel2service/trips/left --5.98--> api: ts-gateway-service-HTTP POST /api/v1/travel2service/trips/left --4.03--> api: ts-gateway-service-/*",
                    "name": "ts-travel2-service-Travel2Controller.queryInfo"
                },
                {
                    "ntype": "api",
                    "id": 208,
                    "score": 7.659708176216866,
                    "path": "api: ts-route-service-SELECT route --5.36--> api: ts-route-service-RouteRepository.findByIds --3.21--> api: ts-route-service-RouteController.queryByIds --3.64--> api: ts-route-service-HTTP POST /api/v1/routeservice/routes/byIds/ --3.39--> api: ts-basic-service-HTTP POST /api/v1/routeservice/routes/byIds/",
                    "name": "ts-route-service-SELECT route"
                },
                {
                    "ntype": "api",
                    "id": 58,
                    "score": 7.553681961679823,
                    "name": "ts-execute-service-HTTP GET /api/v1/executeservice/execute/collected/{orderId}"
                },
                {
                    "ntype": "pod",
                    "id": 25,
                    "score": 5.827812051408411,
                    "path": "pod: ts-travel2-service-5c66d57d58-klvkm --4.95--> api: ts-travel2-service-SELECT ts.trip2",
                    "name": "ts-travel2-service-5c66d57d58-klvkm"
                },
                {
                    "ntype": "api",
                    "id": 279,
                    "score": 4.278022233610342,
                    "path": "api: ts-travel2-service-HTTP POST /api/v1/travel2service/trips/left --5.98--> api: ts-gateway-service-HTTP POST /api/v1/travel2service/trips/left --4.03--> api: ts-gateway-service-/*",
                    "name": "ts-travel2-service-HTTP POST /api/v1/travel2service/trips/left"
                },
                {
                    "ntype": "api",
                    "id": 207,
                    "score": 4.084910957815282,
                    "path": "api: ts-route-service-RouteRepository.findByIds --3.21--> api: ts-route-service-RouteController.queryByIds --3.64--> api: ts-route-service-HTTP POST /api/v1/routeservice/routes/byIds/ --3.39--> api: ts-basic-service-HTTP POST /api/v1/routeservice/routes/byIds/",
                    "name": "ts-route-service-RouteRepository.findByIds"
                },
                {
                    "ntype": "api",
                    "id": 243,
                    "score": 3.3473236139091322,
                    "path": "api: ts-station-service-StationRepository.findByNames --3.41--> api: ts-station-service-StationController.queryForIdBatch",
                    "name": "ts-station-service-StationRepository.findByNames"
                },
                {
                    "ntype": "api",
                    "id": 114,
                    "score": 3.1529915271414772,
                    "name": "ts-inside-payment-service-Transaction.commit"
                },
                {
                    "ntype": "api",
                    "id": 80,
                    "score": 3.065039893550262,
                    "path": "api: ts-gateway-service-/*",
                    "name": "ts-gateway-service-/*"
                },
                {
                    "ntype": "pod",
                    "id": 10,
                    "score": 3.060344777682933,
                    "name": "ts-inside-payment-service-6f94c49ccd-ql78t"
                }
            ]
        },
        {
            "timestamp": 1714045020,
            "level": "pod",
            "cmdb_id": "ts-order-service-5b67c48447-4d4rx",
            "failure_type": "code_delay",
            "cand": [
                {
                    "ntype": "api",
                    "id": 148,
                    "score": 19.519137189902526,
                    "path": "api: ts-order-service-OrderController.modifyOrder --11.02--> api: ts-order-service-HTTP GET /api/v1/orderservice/order/status/{orderId}/{status} --9.02--> api: ts-execute-service-HTTP GET /api/v1/orderservice/order/status/{orderId}/{status} --5.24--> api: ts-execute-service-ExecuteControlller.collectTicket",
                    "name": "ts-order-service-OrderController.modifyOrder"
                },
                {
                    "ntype": "api",
                    "id": 58,
                    "score": 9.483305319176091,
                    "path": "api: ts-execute-service-HTTP GET /api/v1/executeservice/execute/collected/{orderId} --4.66--> api: ts-gateway-service-HTTP GET /api/v1/executeservice/execute/collected/{orderId} --1.86--> api: ts-gateway-service-/*",
                    "name": "ts-execute-service-HTTP GET /api/v1/executeservice/execute/collected/{orderId}"
                },
                {
                    "ntype": "api",
                    "id": 112,
                    "score": 6.949059624929508,
                    "name": "ts-inside-payment-service-Session.persist inside_payment.entity.Money"
                },
                {
                    "ntype": "api",
                    "id": 139,
                    "score": 6.909042275000278,
                    "path": "api: ts-order-service-HTTP GET /api/v1/orderservice/order/status/{orderId}/{status} --9.02--> api: ts-execute-service-HTTP GET /api/v1/orderservice/order/status/{orderId}/{status} --5.24--> api: ts-execute-service-ExecuteControlller.collectTicket",
                    "name": "ts-order-service-HTTP GET /api/v1/orderservice/order/status/{orderId}/{status}"
                },
                {
                    "ntype": "api",
                    "id": 44,
                    "score": 6.067109854321986,
                    "path": "api: ts-contacts-service-ContactsRepository.findById --3.20--> api: ts-contacts-service-ContactsController.getContactsByContactsId --4.40--> api: ts-contacts-service-HTTP GET /api/v1/contactservice/contacts/{id}",
                    "name": "ts-contacts-service-ContactsRepository.findById"
                },
                {
                    "ntype": "api",
                    "id": 243,
                    "score": 4.215484867032508,
                    "name": "ts-station-service-StationRepository.findByNames"
                },
                {
                    "ntype": "api",
                    "id": 62,
                    "score": 4.099078803698391,
                    "path": "api: ts-execute-service-HTTP GET /api/v1/orderservice/order/status/{orderId}/{status} --5.24--> api: ts-execute-service-ExecuteControlller.collectTicket",
                    "name": "ts-execute-service-HTTP GET /api/v1/orderservice/order/status/{orderId}/{status}"
                },
                {
                    "ntype": "pod",
                    "id": 0,
                    "score": 3.702825239532668,
                    "name": "ts-assurance-service-69876c9868-tsp2m"
                },
                {
                    "ntype": "api",
                    "id": 75,
                    "score": 2.8846314256556536,
                    "name": "ts-food-service-INSERT ts.food_order"
                },
                {
                    "ntype": "pod",
                    "id": 25,
                    "score": 2.8806016088212756,
                    "path": "pod: ts-travel2-service-5c66d57d58-klvkm --2.92--> api: ts-travel2-service-SELECT ts.trip2",
                    "name": "ts-travel2-service-5c66d57d58-klvkm"
                }
            ]
        },
        {
            "timestamp": 1714047060,
            "level": "pod",
            "cmdb_id": "ts-travel-service-64469b5b48-zbwtm",
            "failure_type": "code_delay",
            "cand": [
                {
                    "ntype": "api",
                    "id": 169,
                    "score": 15.029924507026283,
                    "path": "api: ts-payment-service-Transaction.commit --4.58--> api: ts-payment-service-PaymentRepository.save --3.25--> api: ts-payment-service-PaymentController.pay --3.68--> api: ts-payment-service-HTTP POST /api/v1/paymentservice/payment --2.95--> api: ts-inside-payment-service-HTTP POST /api/v1/paymentservice/payment",
                    "name": "ts-payment-service-Transaction.commit"
                },
                {
                    "ntype": "api",
                    "id": 22,
                    "score": 13.00476829973557,
                    "path": "api: ts-basic-service-HTTP GET /api/v1/stationservice/stations/id/{stationNameForId} --6.75--> api: ts-basic-service-BasicController.queryForTravel",
                    "name": "ts-basic-service-HTTP GET /api/v1/stationservice/stations/id/{stationNameForId}"
                },
                {
                    "ntype": "api",
                    "id": 270,
                    "score": 8.131478272988108,
                    "path": "api: ts-travel-service-TravelController.getTripAllDetailInfo --2.65--> api: ts-travel-service-HTTP POST /api/v1/travelservice/trip_detail --2.93--> api: ts-preserve-service-HTTP POST /api/v1/travelservice/trip_detail",
                    "name": "ts-travel-service-TravelController.getTripAllDetailInfo"
                },
                {
                    "ntype": "api",
                    "id": 165,
                    "score": 7.132382077104123,
                    "path": "api: ts-payment-service-PaymentRepository.save --3.25--> api: ts-payment-service-PaymentController.pay --3.68--> api: ts-payment-service-HTTP POST /api/v1/paymentservice/payment --2.95--> api: ts-inside-payment-service-HTTP POST /api/v1/paymentservice/payment",
                    "name": "ts-payment-service-PaymentRepository.save"
                },
                {
                    "ntype": "api",
                    "id": 208,
                    "score": 6.826403194864342,
                    "path": "api: ts-route-service-SELECT route --4.20--> api: ts-route-service-RouteRepository.findByIds --2.65--> api: ts-route-service-RouteController.queryByIds --3.68--> api: ts-route-service-HTTP POST /api/v1/routeservice/routes/byIds/ --3.13--> api: ts-basic-service-HTTP POST /api/v1/routeservice/routes/byIds/",
                    "name": "ts-route-service-SELECT route"
                },
                {
                    "ntype": "api",
                    "id": 58,
                    "score": 6.790660447729384,
                    "name": "ts-execute-service-HTTP GET /api/v1/executeservice/execute/collected/{orderId}"
                },
                {
                    "ntype": "api",
                    "id": 235,
                    "score": 6.790636285916316,
                    "path": "api: ts-station-service-HTTP GET /api/v1/stationservice/stations/id/{stationNameForId} --5.10--> api: ts-basic-service-HTTP GET /api/v1/stationservice/stations/id/{stationNameForId} --6.75--> api: ts-basic-service-BasicController.queryForTravel",
                    "name": "ts-station-service-HTTP GET /api/v1/stationservice/stations/id/{stationNameForId}"
                },
                {
                    "ntype": "api",
                    "id": 248,
                    "score": 6.395746798850551,
                    "name": "ts-train-food-service-TrainFoodController.getTrainFoodOfTrip"
                },
                {
                    "ntype": "api",
                    "id": 207,
                    "score": 6.003700715848975,
                    "path": "api: ts-route-service-RouteRepository.findByIds --2.65--> api: ts-route-service-RouteController.queryByIds --3.68--> api: ts-route-service-HTTP POST /api/v1/routeservice/routes/byIds/ --3.13--> api: ts-basic-service-HTTP POST /api/v1/routeservice/routes/byIds/",
                    "name": "ts-route-service-RouteRepository.findByIds"
                },
                {
                    "ntype": "api",
                    "id": 17,
                    "score": 4.82451682789383,
                    "path": "api: ts-basic-service-BasicController.queryForTravel",
                    "name": "ts-basic-service-BasicController.queryForTravel"
                }
            ]
        },
        {
            "timestamp": 1714048440,
            "level": "pod",
            "cmdb_id": "ts-travel2-service-5c66d57d58-klvkm",
            "failure_type": "code_delay",
            "cand": [
                {
                    "ntype": "api",
                    "id": 58,
                    "score": 5.601901075526656,
                    "name": "ts-execute-service-HTTP GET /api/v1/executeservice/execute/collected/{orderId}"
                },
                {
                    "ntype": "api",
                    "id": 202,
                    "score": 5.457710412638408,
                    "path": "api: ts-route-service-HTTP GET /api/v1/routeservice/routes/{routeId} --2.90--> api: ts-travel-service-HTTP GET /api/v1/routeservice/routes/{routeId}",
                    "name": "ts-route-service-HTTP GET /api/v1/routeservice/routes/{routeId}"
                },
                {
                    "ntype": "pod",
                    "id": 24,
                    "score": 4.798729228042916,
                    "path": "pod: ts-travel-service-64469b5b48-zbwtm --11.47--> api: ts-travel-service-SELECT ts.trip",
                    "name": "ts-travel-service-64469b5b48-zbwtm"
                },
                {
                    "ntype": "api",
                    "id": 270,
                    "score": 3.5412972727818364,
                    "name": "ts-travel-service-TravelController.getTripAllDetailInfo"
                },
                {
                    "ntype": "api",
                    "id": 268,
                    "score": 3.346339269553149,
                    "path": "api: ts-travel-service-Transaction.commit",
                    "name": "ts-travel-service-Transaction.commit"
                },
                {
                    "ntype": "api",
                    "id": 221,
                    "score": 3.1346582070381306,
                    "path": "api: ts-seat-service-SeatController.getLeftTicketOfInterval --5.08--> api: ts-seat-service-HTTP POST /api/v1/seatservice/seats/left_tickets --4.33--> api: ts-travel-service-HTTP POST /api/v1/seatservice/seats/left_tickets",
                    "name": "ts-seat-service-SeatController.getLeftTicketOfInterval"
                },
                {
                    "ntype": "pod",
                    "id": 2,
                    "score": 2.7492544379257406,
                    "name": "ts-basic-service-5dc8d4f9fd-58xkn"
                },
                {
                    "ntype": "api",
                    "id": 23,
                    "score": 2.587999342578065,
                    "name": "ts-basic-service-HTTP GET /api/v1/trainservice/trains/byName/{name}"
                },
                {
                    "ntype": "api",
                    "id": 75,
                    "score": 2.5191733170466684,
                    "name": "ts-food-service-INSERT ts.food_order"
                },
                {
                    "ntype": "api",
                    "id": 11,
                    "score": 2.499537240866168,
                    "name": "ts-auth-service-HTTP POST /api/v1/users/login"
                }
            ]
        },
        {
            "timestamp": 1714048860,
            "level": "pod",
            "cmdb_id": "ts-travel2-service-5c66d57d58-klvkm",
            "failure_type": "code_delay",
            "cand": [
                {
                    "ntype": "api",
                    "id": 112,
                    "score": 6.054114541143823,
                    "name": "ts-inside-payment-service-Session.persist inside_payment.entity.Money"
                },
                {
                    "ntype": "api",
                    "id": 58,
                    "score": 4.960494863563895,
                    "name": "ts-execute-service-HTTP GET /api/v1/executeservice/execute/collected/{orderId}"
                },
                {
                    "ntype": "api",
                    "id": 181,
                    "score": 3.8211454163793075,
                    "name": "ts-preserve-other-service-PreserveOtherController.preserve"
                },
                {
                    "ntype": "api",
                    "id": 75,
                    "score": 3.312791891952805,
                    "name": "ts-food-service-INSERT ts.food_order"
                },
                {
                    "ntype": "pod",
                    "id": 20,
                    "score": 3.2561418867593788,
                    "name": "ts-station-food-service-dc4d75dd-vsjjg"
                },
                {
                    "ntype": "pod",
                    "id": 24,
                    "score": 2.8449200405327604,
                    "path": "pod: ts-travel-service-64469b5b48-zbwtm --4.86--> api: ts-travel-service-SELECT ts.trip",
                    "name": "ts-travel-service-64469b5b48-zbwtm"
                },
                {
                    "ntype": "api",
                    "id": 160,
                    "score": 2.642595306709715,
                    "name": "ts-order-service-UPDATE ts.orders"
                },
                {
                    "ntype": "api",
                    "id": 253,
                    "score": 2.4129036233671206,
                    "name": "ts-train-service-SELECT train_type"
                },
                {
                    "ntype": "pod",
                    "id": 2,
                    "score": 2.3398850920994003,
                    "name": "ts-basic-service-5dc8d4f9fd-58xkn"
                },
                {
                    "ntype": "api",
                    "id": 4,
                    "score": 2.2908382217183707,
                    "name": "ts-assurance-service-INSERT ts.assurance"
                }
            ]
        },
        {
            "timestamp": 1714049280,
            "level": "pod",
            "cmdb_id": "ts-travel2-service-5c66d57d58-klvkm",
            "failure_type": "code_delay",
            "cand": [
                {
                    "ntype": "api",
                    "id": 112,
                    "score": 7.145864906766554,
                    "name": "ts-inside-payment-service-Session.persist inside_payment.entity.Money"
                },
                {
                    "ntype": "pod",
                    "id": 19,
                    "score": 6.925460483804102,
                    "name": "ts-security-service-cb9788d56-v24jq"
                },
                {
                    "ntype": "api",
                    "id": 135,
                    "score": 6.915397835894986,
                    "name": "ts-order-other-service-Session.merge other.entity.Order"
                },
                {
                    "ntype": "api",
                    "id": 181,
                    "score": 5.685940696506783,
                    "name": "ts-preserve-other-service-PreserveOtherController.preserve"
                },
                {
                    "ntype": "api",
                    "id": 58,
                    "score": 4.775443419500288,
                    "name": "ts-execute-service-HTTP GET /api/v1/executeservice/execute/collected/{orderId}"
                },
                {
                    "ntype": "pod",
                    "id": 25,
                    "score": 4.5818828117324655,
                    "path": "pod: ts-travel2-service-5c66d57d58-klvkm --5.01--> api: ts-travel2-service-SELECT ts.trip2",
                    "name": "ts-travel2-service-5c66d57d58-klvkm"
                },
                {
                    "ntype": "api",
                    "id": 270,
                    "score": 4.494238422387331,
                    "name": "ts-travel-service-TravelController.getTripAllDetailInfo"
                },
                {
                    "ntype": "pod",
                    "id": 24,
                    "score": 4.076103082307212,
                    "name": "ts-travel-service-64469b5b48-zbwtm"
                },
                {
                    "ntype": "api",
                    "id": 136,
                    "score": 3.839803858347642,
                    "name": "ts-order-other-service-Transaction.commit"
                },
                {
                    "ntype": "api",
                    "id": 102,
                    "score": 3.376067787754497,
                    "name": "ts-inside-payment-service-INSERT ts.inside_money"
                }
            ]
        },
        {
            "timestamp": 1714061040,
            "level": "pod",
            "cmdb_id": "ts-train-service-86f5f97bc9-f7687",
            "failure_type": "exception",
            "cand": [
                {
                    "ntype": "api",
                    "id": 255,
                    "score": 37.03402113911197,
                    "path": "api: ts-train-service-TrainController.retrieveByName --18.32--> api: ts-train-service-HTTP POST /api/v1/trainservice/trains/byNames --21.11--> api: ts-basic-service-HTTP POST /api/v1/trainservice/trains/byNames --15.30--> api: ts-basic-service-BasicController.queryForTravels --4.01--> api: ts-basic-service-HTTP POST /api/v1/basicservice/basic/travels --6.48--> api: ts-travel2-service-HTTP POST /api/v1/basicservice/basic/travels --3.51--> api: ts-travel2-service-Travel2Controller.queryInfo --3.15--> api: ts-travel2-service-HTTP POST /api/v1/travel2service/trips/left --4.27--> api: ts-gateway-service-HTTP POST /api/v1/travel2service/trips/left",
                    "name": "ts-train-service-TrainController.retrieveByName"
                },
                {
                    "ntype": "api",
                    "id": 257,
                    "score": 28.355199344195384,
                    "path": "api: ts-train-service-TrainTypeRepository.findByNames --6.35--> api: ts-train-service-TrainController.retrieveByName --18.32--> api: ts-train-service-HTTP POST /api/v1/trainservice/trains/byNames --21.11--> api: ts-basic-service-HTTP POST /api/v1/trainservice/trains/byNames --15.30--> api: ts-basic-service-BasicController.queryForTravels --4.01--> api: ts-basic-service-HTTP POST /api/v1/basicservice/basic/travels --6.48--> api: ts-travel2-service-HTTP POST /api/v1/basicservice/basic/travels --3.51--> api: ts-travel2-service-Travel2Controller.queryInfo --3.15--> api: ts-travel2-service-HTTP POST /api/v1/travel2service/trips/left --4.27--> api: ts-gateway-service-HTTP POST /api/v1/travel2service/trips/left",
                    "name": "ts-train-service-TrainTypeRepository.findByNames"
                },
                {
                    "ntype": "api",
                    "id": 251,
                    "score": 28.090126720410147,
                    "path": "api: ts-train-service-HTTP POST /api/v1/trainservice/trains/byNames --21.11--> api: ts-basic-service-HTTP POST /api/v1/trainservice/trains/byNames --15.30--> api: ts-basic-service-BasicController.queryForTravels --4.01--> api: ts-basic-service-HTTP POST /api/v1/basicservice/basic/travels --6.48--> api: ts-travel2-service-HTTP POST /api/v1/basicservice/basic/travels --3.51--> api: ts-travel2-service-Travel2Controller.queryInfo --3.15--> api: ts-travel2-service-HTTP POST /api/v1/travel2service/trips/left --4.27--> api: ts-gateway-service-HTTP POST /api/v1/travel2service/trips/left",
                    "name": "ts-train-service-HTTP POST /api/v1/trainservice/trains/byNames"
                },
                {
                    "ntype": "api",
                    "id": 254,
                    "score": 27.029432342459167,
                    "path": "api: ts-train-service-SELECT ts.train_type --10.18--> api: ts-train-service-SELECT train_type --7.00--> api: ts-train-service-TrainTypeRepository.findByNames --6.35--> api: ts-train-service-TrainController.retrieveByName --18.32--> api: ts-train-service-HTTP POST /api/v1/trainservice/trains/byNames --21.11--> api: ts-basic-service-HTTP POST /api/v1/trainservice/trains/byNames --15.30--> api: ts-basic-service-BasicController.queryForTravels --4.01--> api: ts-basic-service-HTTP POST /api/v1/basicservice/basic/travels --6.48--> api: ts-travel2-service-HTTP POST /api/v1/basicservice/basic/travels --3.51--> api: ts-travel2-service-Travel2Controller.queryInfo --3.15--> api: ts-travel2-service-HTTP POST /api/v1/travel2service/trips/left --4.27--> api: ts-gateway-service-HTTP POST /api/v1/travel2service/trips/left",
                    "name": "ts-train-service-SELECT ts.train_type"
                },
                {
                    "ntype": "api",
                    "id": 253,
                    "score": 25.537787299431194,
                    "path": "api: ts-train-service-SELECT train_type --7.00--> api: ts-train-service-TrainTypeRepository.findByNames --6.35--> api: ts-train-service-TrainController.retrieveByName --18.32--> api: ts-train-service-HTTP POST /api/v1/trainservice/trains/byNames --21.11--> api: ts-basic-service-HTTP POST /api/v1/trainservice/trains/byNames --15.30--> api: ts-basic-service-BasicController.queryForTravels --4.01--> api: ts-basic-service-HTTP POST /api/v1/basicservice/basic/travels --6.48--> api: ts-travel2-service-HTTP POST /api/v1/basicservice/basic/travels --3.51--> api: ts-travel2-service-Travel2Controller.queryInfo --3.15--> api: ts-travel2-service-HTTP POST /api/v1/travel2service/trips/left --4.27--> api: ts-gateway-service-HTTP POST /api/v1/travel2service/trips/left",
                    "name": "ts-train-service-SELECT train_type"
                },
                {
                    "ntype": "api",
                    "id": 29,
                    "score": 22.275373414652307,
                    "path": "api: ts-basic-service-HTTP POST /api/v1/trainservice/trains/byNames --15.30--> api: ts-basic-service-BasicController.queryForTravels --4.01--> api: ts-basic-service-HTTP POST /api/v1/basicservice/basic/travels --6.48--> api: ts-travel2-service-HTTP POST /api/v1/basicservice/basic/travels --3.51--> api: ts-travel2-service-Travel2Controller.queryInfo --3.15--> api: ts-travel2-service-HTTP POST /api/v1/travel2service/trips/left --4.27--> api: ts-gateway-service-HTTP POST /api/v1/travel2service/trips/left",
                    "name": "ts-basic-service-HTTP POST /api/v1/trainservice/trains/byNames"
                },
                {
                    "ntype": "api",
                    "id": 40,
                    "score": 20.73360986498867,
                    "path": "api: ts-config-service-HTTP GET /api/v1/configservice/configs/{configName} --11.82--> api: ts-seat-service-HTTP GET /api/v1/configservice/configs/{configName} --6.67--> api: ts-seat-service-SeatController.getLeftTicketOfInterval --6.11--> api: ts-seat-service-HTTP POST /api/v1/seatservice/seats/left_tickets --4.85--> api: ts-travel-service-HTTP POST /api/v1/seatservice/seats/left_tickets",
                    "name": "ts-config-service-HTTP GET /api/v1/configservice/configs/{configName}"
                },
                {
                    "ntype": "api",
                    "id": 18,
                    "score": 18.224106394773575,
                    "path": "api: ts-basic-service-BasicController.queryForTravels --4.01--> api: ts-basic-service-HTTP POST /api/v1/basicservice/basic/travels --6.48--> api: ts-travel2-service-HTTP POST /api/v1/basicservice/basic/travels --3.51--> api: ts-travel2-service-Travel2Controller.queryInfo --3.15--> api: ts-travel2-service-HTTP POST /api/v1/travel2service/trips/left --4.27--> api: ts-gateway-service-HTTP POST /api/v1/travel2service/trips/left",
                    "name": "ts-basic-service-BasicController.queryForTravels"
                },
                {
                    "ntype": "api",
                    "id": 215,
                    "score": 10.654641373877102,
                    "path": "api: ts-seat-service-HTTP GET /api/v1/configservice/configs/{configName} --6.67--> api: ts-seat-service-SeatController.getLeftTicketOfInterval --6.11--> api: ts-seat-service-HTTP POST /api/v1/seatservice/seats/left_tickets --4.85--> api: ts-travel-service-HTTP POST /api/v1/seatservice/seats/left_tickets",
                    "name": "ts-seat-service-HTTP GET /api/v1/configservice/configs/{configName}"
                },
                {
                    "ntype": "api",
                    "id": 58,
                    "score": 8.849430166872189,
                    "name": "ts-execute-service-HTTP GET /api/v1/executeservice/execute/collected/{orderId}"
                }
            ]
        },
        {
            "timestamp": 1714062000,
            "level": "pod",
            "cmdb_id": "ts-train-service-86f5f97bc9-f7687",
            "failure_type": "exception",
            "cand": [
                {
                    "ntype": "api",
                    "id": 255,
                    "score": 39.80228589876026,
                    "path": "api: ts-train-service-TrainController.retrieveByName --17.51--> api: ts-train-service-HTTP POST /api/v1/trainservice/trains/byNames --22.36--> api: ts-basic-service-HTTP POST /api/v1/trainservice/trains/byNames --15.18--> api: ts-basic-service-BasicController.queryForTravels --4.03--> api: ts-basic-service-HTTP POST /api/v1/basicservice/basic/travels --6.15--> api: ts-travel2-service-HTTP POST /api/v1/basicservice/basic/travels --2.75--> api: ts-travel2-service-Travel2Controller.queryInfo --4.36--> api: ts-travel2-service-HTTP POST /api/v1/travel2service/trips/left --3.35--> api: ts-gateway-service-HTTP POST /api/v1/travel2service/trips/left",
                    "name": "ts-train-service-TrainController.retrieveByName"
                },
                {
                    "ntype": "api",
                    "id": 251,
                    "score": 28.01263868737169,
                    "path": "api: ts-train-service-HTTP POST /api/v1/trainservice/trains/byNames --22.36--> api: ts-basic-service-HTTP POST /api/v1/trainservice/trains/byNames --15.18--> api: ts-basic-service-BasicController.queryForTravels --4.03--> api: ts-basic-service-HTTP POST /api/v1/basicservice/basic/travels --6.15--> api: ts-travel2-service-HTTP POST /api/v1/basicservice/basic/travels --2.75--> api: ts-travel2-service-Travel2Controller.queryInfo --4.36--> api: ts-travel2-service-HTTP POST /api/v1/travel2service/trips/left --3.35--> api: ts-gateway-service-HTTP POST /api/v1/travel2service/trips/left",
                    "name": "ts-train-service-HTTP POST /api/v1/trainservice/trains/byNames"
                },
                {
                    "ntype": "api",
                    "id": 29,
                    "score": 19.623828574976145,
                    "path": "api: ts-basic-service-HTTP POST /api/v1/trainservice/trains/byNames --15.18--> api: ts-basic-service-BasicController.queryForTravels --4.03--> api: ts-basic-service-HTTP POST /api/v1/basicservice/basic/travels --6.15--> api: ts-travel2-service-HTTP POST /api/v1/basicservice/basic/travels --2.75--> api: ts-travel2-service-Travel2Controller.queryInfo --4.36--> api: ts-travel2-service-HTTP POST /api/v1/travel2service/trips/left --3.35--> api: ts-gateway-service-HTTP POST /api/v1/travel2service/trips/left",
                    "name": "ts-basic-service-HTTP POST /api/v1/trainservice/trains/byNames"
                },
                {
                    "ntype": "api",
                    "id": 18,
                    "score": 18.1362374838902,
                    "path": "api: ts-basic-service-BasicController.queryForTravels --4.03--> api: ts-basic-service-HTTP POST /api/v1/basicservice/basic/travels --6.15--> api: ts-travel2-service-HTTP POST /api/v1/basicservice/basic/travels --2.75--> api: ts-travel2-service-Travel2Controller.queryInfo --4.36--> api: ts-travel2-service-HTTP POST /api/v1/travel2service/trips/left --3.35--> api: ts-gateway-service-HTTP POST /api/v1/travel2service/trips/left",
                    "name": "ts-basic-service-BasicController.queryForTravels"
                },
                {
                    "ntype": "api",
                    "id": 250,
                    "score": 9.462279802230102,
                    "path": "api: ts-train-service-HTTP GET /api/v1/trainservice/trains/byName/{name}",
                    "name": "ts-train-service-HTTP GET /api/v1/trainservice/trains/byName/{name}"
                },
                {
                    "ntype": "api",
                    "id": 25,
                    "score": 6.115494397681257,
                    "path": "api: ts-basic-service-HTTP POST /api/v1/basicservice/basic/travels --6.15--> api: ts-travel2-service-HTTP POST /api/v1/basicservice/basic/travels --2.75--> api: ts-travel2-service-Travel2Controller.queryInfo --4.36--> api: ts-travel2-service-HTTP POST /api/v1/travel2service/trips/left --3.35--> api: ts-gateway-service-HTTP POST /api/v1/travel2service/trips/left",
                    "name": "ts-basic-service-HTTP POST /api/v1/basicservice/basic/travels"
                },
                {
                    "ntype": "api",
                    "id": 237,
                    "score": 5.9384974103461765,
                    "path": "api: ts-station-service-SELECT Station --3.42--> api: ts-station-service-StationRepository.findByName --3.34--> api: ts-station-service-StationController.queryForStationId",
                    "name": "ts-station-service-SELECT Station"
                },
                {
                    "ntype": "api",
                    "id": 58,
                    "score": 5.510004505328646,
                    "name": "ts-execute-service-HTTP GET /api/v1/executeservice/execute/collected/{orderId}"
                },
                {
                    "ntype": "api",
                    "id": 242,
                    "score": 4.762309801425247,
                    "path": "api: ts-station-service-StationRepository.findByName --3.34--> api: ts-station-service-StationController.queryForStationId",
                    "name": "ts-station-service-StationRepository.findByName"
                },
                {
                    "ntype": "api",
                    "id": 160,
                    "score": 3.7243506347487485,
                    "name": "ts-order-service-UPDATE ts.orders"
                }
            ]
        },
        {
            "timestamp": 1714062480,
            "level": "pod",
            "cmdb_id": "ts-order-service-5b67c48447-4d4rx",
            "failure_type": "exception",
            "cand": [
                {
                    "ntype": "api",
                    "id": 148,
                    "score": 15.281445188128306,
                    "path": "api: ts-order-service-OrderController.modifyOrder --10.70--> api: ts-order-service-HTTP GET /api/v1/orderservice/order/status/{orderId}/{status} --8.12--> api: ts-inside-payment-service-HTTP GET /api/v1/orderservice/order/status/{orderId}/{status}",
                    "name": "ts-order-service-OrderController.modifyOrder"
                },
                {
                    "ntype": "api",
                    "id": 100,
                    "score": 11.323013873405237,
                    "path": "api: ts-inside-payment-service-HTTP POST /api/v1/inside_pay_service/inside_payment --2.72--> api: ts-gateway-service-HTTP POST /api/v1/inside_pay_service/inside_payment --3.47--> api: ts-gateway-service-/*",
                    "name": "ts-inside-payment-service-HTTP POST /api/v1/inside_pay_service/inside_payment"
                },
                {
                    "ntype": "api",
                    "id": 178,
                    "score": 8.654145429483023,
                    "name": "ts-preserve-other-service-HTTP POST /api/v1/preserveotherservice/preserveOther"
                },
                {
                    "ntype": "api",
                    "id": 170,
                    "score": 8.515781889488817,
                    "name": "ts-preserve-other-service-BasicErrorController.error"
                },
                {
                    "ntype": "api",
                    "id": 112,
                    "score": 6.749094337605891,
                    "name": "ts-inside-payment-service-Session.persist inside_payment.entity.Money"
                },
                {
                    "ntype": "api",
                    "id": 58,
                    "score": 5.135855155021258,
                    "name": "ts-execute-service-HTTP GET /api/v1/executeservice/execute/collected/{orderId}"
                },
                {
                    "ntype": "api",
                    "id": 104,
                    "score": 4.791464394927597,
                    "path": "api: ts-inside-payment-service-InsidePaymentController.drawBack --3.24--> api: ts-inside-payment-service-HTTP GET /api/v1/inside_pay_service/inside_payment/drawback/{userId}/{money} --3.44--> api: ts-cancel-service-HTTP GET /api/v1/inside_pay_service/inside_payment/drawback/{userId}/{money} --3.09--> api: ts-cancel-service-CancelController.cancelTicket --3.48--> api: ts-cancel-service-HTTP GET /api/v1/cancelservice/cancel/{orderId}/{loginId} --3.39--> api: ts-gateway-service-HTTP GET /api/v1/cancelservice/cancel/{orderId}/{loginId}",
                    "name": "ts-inside-payment-service-InsidePaymentController.drawBack"
                },
                {
                    "ntype": "api",
                    "id": 132,
                    "score": 4.710542441144194,
                    "path": "api: ts-order-other-service-SELECT Order --5.40--> api: ts-order-other-service-OrderOtherRepository.findByAccountId",
                    "name": "ts-order-other-service-SELECT Order"
                },
                {
                    "ntype": "api",
                    "id": 160,
                    "score": 4.2785983993153165,
                    "name": "ts-order-service-UPDATE ts.orders"
                },
                {
                    "ntype": "api",
                    "id": 93,
                    "score": 4.147779106810932,
                    "path": "api: ts-inside-payment-service-AddMoneyRepository.save",
                    "name": "ts-inside-payment-service-AddMoneyRepository.save"
                }
            ]
        },
        {
            "timestamp": 1714064280,
            "level": "pod",
            "cmdb_id": "ts-travel-service-64469b5b48-zbwtm",
            "failure_type": "exception",
            "cand": [
                {
                    "ntype": "api",
                    "id": 292,
                    "score": 11.32623023347388,
                    "path": "api: ts-verification-code-service-HTTP GET /api/v1/verifycode/verify/{verifyCode} --7.03--> api: ts-auth-service-HTTP GET /api/v1/verifycode/verify/{verifyCode}",
                    "name": "ts-verification-code-service-HTTP GET /api/v1/verifycode/verify/{verifyCode}"
                },
                {
                    "ntype": "api",
                    "id": 10,
                    "score": 9.078060307259165,
                    "path": "api: ts-auth-service-HTTP GET /api/v1/verifycode/verify/{verifyCode}",
                    "name": "ts-auth-service-HTTP GET /api/v1/verifycode/verify/{verifyCode}"
                },
                {
                    "ntype": "api",
                    "id": 112,
                    "score": 6.483669291394674,
                    "name": "ts-inside-payment-service-Session.persist inside_payment.entity.Money"
                },
                {
                    "ntype": "api",
                    "id": 58,
                    "score": 6.104900099818574,
                    "name": "ts-execute-service-HTTP GET /api/v1/executeservice/execute/collected/{orderId}"
                },
                {
                    "ntype": "api",
                    "id": 144,
                    "score": 4.259431130749215,
                    "name": "ts-order-service-INSERT ts.orders"
                },
                {
                    "ntype": "api",
                    "id": 145,
                    "score": 3.3111197471846285,
                    "name": "ts-order-service-OrderController.createNewOrder"
                },
                {
                    "ntype": "api",
                    "id": 158,
                    "score": 2.9024996354769734,
                    "name": "ts-order-service-Session.merge order.entity.Order"
                },
                {
                    "ntype": "api",
                    "id": 11,
                    "score": 2.855915753431641,
                    "name": "ts-auth-service-HTTP POST /api/v1/users/login"
                },
                {
                    "ntype": "api",
                    "id": 121,
                    "score": 2.588333058771227,
                    "name": "ts-order-other-service-INSERT ts.orders_other"
                },
                {
                    "ntype": "api",
                    "id": 135,
                    "score": 2.572011055337545,
                    "name": "ts-order-other-service-Session.merge other.entity.Order"
                }
            ]
        },
        {
            "timestamp": 1714064700,
            "level": "pod",
            "cmdb_id": "ts-travel-service-64469b5b48-zbwtm",
            "failure_type": "exception",
            "cand": [
                {
                    "ntype": "api",
                    "id": 58,
                    "score": 7.385586732552667,
                    "name": "ts-execute-service-HTTP GET /api/v1/executeservice/execute/collected/{orderId}"
                },
                {
                    "ntype": "api",
                    "id": 242,
                    "score": 7.187519918334869,
                    "path": "api: ts-station-service-StationRepository.findByName --5.57--> api: ts-station-service-StationController.queryForStationId --2.61--> api: ts-station-service-HTTP GET /api/v1/stationservice/stations/id/{stationNameForId}",
                    "name": "ts-station-service-StationRepository.findByName"
                },
                {
                    "ntype": "api",
                    "id": 158,
                    "score": 6.4820787269681475,
                    "name": "ts-order-service-Session.merge order.entity.Order"
                },
                {
                    "ntype": "api",
                    "id": 227,
                    "score": 5.039720909371126,
                    "path": "api: ts-security-service-SELECT ts.security_config --4.61--> api: ts-security-service-SELECT SecurityConfig --4.11--> api: ts-security-service-SecurityRepository.findByName",
                    "name": "ts-security-service-SELECT ts.security_config"
                },
                {
                    "ntype": "api",
                    "id": 75,
                    "score": 4.299605082475666,
                    "name": "ts-food-service-INSERT ts.food_order"
                },
                {
                    "ntype": "pod",
                    "id": 24,
                    "score": 3.9913309248805833,
                    "path": "pod: ts-travel-service-64469b5b48-zbwtm --7.20--> api: ts-travel-service-SELECT ts.trip",
                    "name": "ts-travel-service-64469b5b48-zbwtm"
                },
                {
                    "ntype": "pod",
                    "id": 6,
                    "score": 3.9011331517134193,
                    "path": "pod: ts-delivery-service-7d97b69596-jngz4 --4.96--> api: ts-delivery-service-INSERT ts.delivery",
                    "name": "ts-delivery-service-7d97b69596-jngz4"
                },
                {
                    "ntype": "api",
                    "id": 220,
                    "score": 3.7870444781917643,
                    "name": "ts-seat-service-SeatController.create"
                },
                {
                    "ntype": "api",
                    "id": 159,
                    "score": 3.607885888519919,
                    "name": "ts-order-service-Transaction.commit"
                },
                {
                    "ntype": "api",
                    "id": 112,
                    "score": 3.2472740003492406,
                    "name": "ts-inside-payment-service-Session.persist inside_payment.entity.Money"
                }
            ]
        },
        {
            "timestamp": 1714066140,
            "level": "pod",
            "cmdb_id": "ts-travel2-service-5c66d57d58-klvkm",
            "failure_type": "exception",
            "cand": [
                {
                    "ntype": "api",
                    "id": 41,
                    "score": 6.501953532971686,
                    "path": "api: ts-config-service-SELECT Config --4.38--> api: ts-config-service-ConfigRepository.findByName --5.37--> api: ts-config-service-ConfigController.retrieve --3.11--> api: ts-config-service-HTTP GET /api/v1/configservice/configs/{configName}",
                    "name": "ts-config-service-SELECT Config"
                },
                {
                    "ntype": "api",
                    "id": 200,
                    "score": 6.381201623137809,
                    "path": "api: ts-price-service-SELECT price_config --4.55--> api: ts-price-service-PriceConfigRepository.findByRouteIdsAndTrainTypes --3.28--> api: ts-price-service-PriceController.query --3.62--> api: ts-price-service-HTTP POST /api/v1/priceservice/prices/byRouteIdsAndTrainTypes --2.66--> api: ts-basic-service-HTTP POST /api/v1/priceservice/prices/byRouteIdsAndTrainTypes",
                    "name": "ts-price-service-SELECT price_config"
                },
                {
                    "ntype": "api",
                    "id": 58,
                    "score": 5.927813768473872,
                    "name": "ts-execute-service-HTTP GET /api/v1/executeservice/execute/collected/{orderId}"
                },
                {
                    "ntype": "api",
                    "id": 112,
                    "score": 5.793022415981156,
                    "name": "ts-inside-payment-service-Session.persist inside_payment.entity.Money"
                },
                {
                    "ntype": "api",
                    "id": 39,
                    "score": 4.460795209830836,
                    "path": "api: ts-config-service-ConfigRepository.findByName --5.37--> api: ts-config-service-ConfigController.retrieve --3.11--> api: ts-config-service-HTTP GET /api/v1/configservice/configs/{configName}",
                    "name": "ts-config-service-ConfigRepository.findByName"
                },
                {
                    "ntype": "api",
                    "id": 197,
                    "score": 4.121157571563458,
                    "path": "api: ts-price-service-PriceConfigRepository.findByRouteIdsAndTrainTypes --3.28--> api: ts-price-service-PriceController.query --3.62--> api: ts-price-service-HTTP POST /api/v1/priceservice/prices/byRouteIdsAndTrainTypes --2.66--> api: ts-basic-service-HTTP POST /api/v1/priceservice/prices/byRouteIdsAndTrainTypes",
                    "name": "ts-price-service-PriceConfigRepository.findByRouteIdsAndTrainTypes"
                },
                {
                    "ntype": "api",
                    "id": 101,
                    "score": 3.765123686449657,
                    "name": "ts-inside-payment-service-HTTP POST /api/v1/paymentservice/payment"
                },
                {
                    "ntype": "api",
                    "id": 283,
                    "score": 3.613859972005618,
                    "name": "ts-travel2-service-Travel2Controller.getTripAllDetailInfo"
                },
                {
                    "ntype": "api",
                    "id": 37,
                    "score": 3.0269377597813083,
                    "name": "ts-cancel-service-HTTP PUT /api/v1/orderservice/order"
                },
                {
                    "ntype": "api",
                    "id": 75,
                    "score": 3.0198715849090276,
                    "name": "ts-food-service-INSERT ts.food_order"
                }
            ]
        }
    ]
}